swarm_explainer/__init__.py
swarm_explainer/explainer.py
swarm_explainer/utils.py
swarm_explainer-0.0.1.dist-info/LICENSE
swarm_explainer-0.0.1.dist-info/METADATA
swarm_explainer-0.0.1.dist-info/WHEEL
swarm_explainer-0.0.1.dist-info/top_level.txt
swarm_explainer-0.0.1.dist-info/RECORD
