Metadata-Version: 2.1
Name: swarm-explainer
Version: 0.0.1
Summary: Model-agnostic explanations using feature perturbations
Home-page: https://github.com/wilsonjr/SwarmExplainer
Author: Wilson E. Marcílio-Jr
Author-email: wilson_jr@outlook.com
License: UNKNOWN
Platform: UNKNOWN
License-File: LICENSE
Requires-Dist: pandas
Requires-Dist: sklearn
Requires-Dist: numpy
Requires-Dist: shap
Requires-Dist: seaborn
Provides-Extra: test
Requires-Dist: pytest ; extra == 'test'
